eulxml/__init__.py
eulxml/catalog.py
eulxml/forms/__init__.py
eulxml/forms/xmlobject.py
eulxml/schema_data/catalog.xml
eulxml/schema_data/ead.xsd
eulxml/schema_data/mail-account.xsd
eulxml/schema_data/mods-3-4.xsd
eulxml/schema_data/mods.xsd
eulxml/schema_data/oai_dc.xsd
eulxml/schema_data/premis-v2-1.xsd
eulxml/schema_data/premis.xsd
eulxml/schema_data/tei_all.xsd
eulxml/schema_data/xlink.xsd
eulxml/utils/__init__.py
eulxml/utils/compat.py
eulxml/xmlmap/__init__.py
eulxml/xmlmap/cerp.py
eulxml/xmlmap/core.py
eulxml/xmlmap/dc.py
eulxml/xmlmap/eadmap.py
eulxml/xmlmap/fields.py
eulxml/xmlmap/mods.py
eulxml/xmlmap/premis.py
eulxml/xmlmap/teimap.py
eulxml/xpath/__init__.py
eulxml/xpath/ast.py
eulxml/xpath/core.py
eulxml/xpath/lexrules.py
eulxml/xpath/lextab.py
eulxml/xpath/parserules.py
eulxml/xpath/parsetab.py
eulxml-1.1.3.dist-info/DESCRIPTION.rst
eulxml-1.1.3.dist-info/METADATA
eulxml-1.1.3.dist-info/metadata.json
eulxml-1.1.3.dist-info/RECORD
eulxml-1.1.3.dist-info/top_level.txt
eulxml-1.1.3.dist-info/WHEEL
