Metadata-Version: 2.0
Name: eulxml
Version: 1.1.3
Summary: XPath-based XML data binding, with Django form support
Home-page: https://github.com/emory-libraries/eulxml
Author: Emory University Libraries
Author-email: libsysdev-l@listserv.cc.emory.edu
License: Apache License, Version 2.0
Platform: UNKNOWN
Classifier: Development Status :: 5 - Production/Stable
Classifier: Framework :: Django
Classifier: Intended Audience :: Developers
Classifier: License :: OSI Approved :: Apache Software License
Classifier: Natural Language :: English
Classifier: Operating System :: OS Independent
Classifier: Programming Language :: Python
Classifier: Programming Language :: Python :: 2
Classifier: Programming Language :: Python :: 2.6
Classifier: Programming Language :: Python :: 2.7
Classifier: Programming Language :: Python :: 3
Classifier: Programming Language :: Python :: 3.3
Classifier: Programming Language :: Python :: 3.4
Classifier: Programming Language :: Python :: 3.5
Classifier: Topic :: Software Development :: Libraries :: Python Modules
Classifier: Topic :: Text Processing :: Markup :: XML
Requires-Dist: ply (>=3.8)
Requires-Dist: lxml (>=3.4)
Requires-Dist: six (>=1.10)
Provides-Extra: dev
Requires-Dist: sphinx (>=1.3.5); extra == 'dev'
Requires-Dist: coverage; extra == 'dev'
Requires-Dist: Django (<1.9); extra == 'dev'
Requires-Dist: rdflib (>=3.0); extra == 'dev'
Requires-Dist: mock; extra == 'dev'
Requires-Dist: nose; extra == 'dev'
Requires-Dist: tox; extra == 'dev'
Requires-Dist: requests; extra == 'dev'
Provides-Extra: django
Requires-Dist: Django (<1.9); extra == 'django'
Provides-Extra: rdf
Requires-Dist: rdflib (>=3.0); extra == 'rdf'
